{
        "imageUrl": "assets/images/bad_art/good_art2.png", 
        "title": "Dora Maar with Cat", 
        "artist": "Pablo Picasso",
        "nationality": "Spanish",
        "year": "1941",
        "medium": "Oil on canvas",
        "size": "128.3 cm × 95.3 cm",
        "snippet": "The painter's lover, seated on a chair with a small cat perched on her shoulders.  One of the world's most expensive paintings, it was sold at auction in 2006 in New York to an anonymous Russian bidder for US$95,216,000."
}